coursebox_testing/__init__.py
coursebox_testing/testing/__init__.py
coursebox_testing/testing/testing.py
coursebox_testing-0.1.0.dist-info/LICENSE
coursebox_testing-0.1.0.dist-info/METADATA
coursebox_testing-0.1.0.dist-info/WHEEL
coursebox_testing-0.1.0.dist-info/top_level.txt
coursebox_testing-0.1.0.dist-info/RECORD
