Metadata-Version: 2.1
Name: coursebox_testing
Version: 0.1.0
Summary: A course management system currently used at DTU (testing software)
Home-page: https://lab.compute.dtu.dk/tuhe/coursebox_testing
Author: Tue Herlau
Author-email: tuhe@dtu.dk
License: MIT
Project-URL: Bug Tracker, https://lab.compute.dtu.dk/tuhe/coursebox_testing/issues
Classifier: Programming Language :: Python :: 3
Classifier: License :: OSI Approved :: MIT License
Classifier: Operating System :: OS Independent
Requires-Python: >=3.8
License-File: LICENSE
Requires-Dist: unitgrade
Requires-Dist: tabulate
Requires-Dist: pydocstyle
Requires-Dist: darglint
